[
  {
    "source_id": "https://api.cdr.land/v1/docs/documents",
    "record_id": "02204021e5b0dfc7ef8b406b88bacc57065753c872ac9722011e56da8d3fa9f1dd",
    "name": "NI 43-101 Technical Report for the Springer Project in Nevada, United States dated May 2009.pdf",
    "location_info": {
      "location": "POINT(118.13278 40.78222)",
      "crs": {
        "normalized_uri": "https://minmod.isi.edu/resource/Q701",
        "observed_name": "WGS84",
        "confidence": 1,
        "source": "Inferlink Extraction v2"
      },
      "country": {
        "normalized_uri": "https://minmod.isi.edu/resource/Q1235",
        "observed_name": "United States",
        "confidence": 1,
        "source": "Inferlink Extraction v2"
      },
      "state_or_province": {
        "normalized_uri": "https://minmod.isi.edu/resource/Q6876",
        "observed_name": "Nevada",
        "confidence": 1,
        "source": "Inferlink Extraction v2"
      }
    },
    "mineral_inventory": [
      {
        "commodity": {
          "normalized_uri": "https://minmod.isi.edu/resource/Q615",
          "observed_name": "tungsten",
          "confidence": 1,
          "source": "Inferlink Extraction v2"
        },
        "category": [
          {
            "normalized_uri": "https://minmod.isi.edu/resource/Indicated",
            "observed_name": "indicated",
            "confidence": 1,
            "source": "Inferlink Extraction v2"
          }
        ],
        "material_form": {
          "normalized_uri": "https://minmod.isi.edu/resource/Q1304",
          "observed_name": "WO3",
          "confidence": 1,
          "source": "Inferlink Extraction v2"
        },
        "ore": {
          "unit": {
            "normalized_uri": "https://minmod.isi.edu/resource/Q200",
            "observed_name": "kt",
            "confidence": 1,
            "source": "Inferlink Extraction v2"
          },
          "value": 274000.0
        },
        "grade": {
          "unit": {
            "normalized_uri": "https://minmod.isi.edu/resource/Q201",
            "observed_name": "%",
            "confidence": 1,
            "source": "Inferlink Extraction v2"
          },
          "value": 0.619
        },
        "cutoff_grade": {
          "unit": {
            "normalized_uri": "https://minmod.isi.edu/resource/Q201",
            "observed_name": "%",
            "confidence": 1,
            "source": "Inferlink Extraction v2"
          },
          "value": 0.3
        },
        "contained_metal": 1696.06,
        "reference": {
          "document": {
            "title": "NI 43-101 Technical Report for the Springer Project in Nevada, United States dated May 2009.pdf",
            "authors": [
              "Bart A. Stryhas"
            ],
            "year": 2009,
            "month": 5,
            "description": "This report provides a comprehensive review of the historical exploration activities at the Springer Facility in Nevada and a current resource estimate based on drilling data.",
            "uri": "https://api.cdr.land/v1/docs/documents/02204021e5b0dfc7ef8b406b88bacc57065753c872ac9722011e56da8d3fa9f1dd"
          },
          "page_info": [
            {
              "page": 7
            }
          ]
        },
        "date": "2009-5",
        "zone": "sutton i & ii"
      },
      {
        "commodity": {
          "normalized_uri": "https://minmod.isi.edu/resource/Q615",
          "observed_name": "tungsten",
          "confidence": 1,
          "source": "Inferlink Extraction v2"
        },
        "category": [
          {
            "normalized_uri": "https://minmod.isi.edu/resource/Inferred",
            "observed_name": "inferred",
            "confidence": 1,
            "source": "Inferlink Extraction v2"
          }
        ],
        "material_form": {
          "normalized_uri": "https://minmod.isi.edu/resource/Q1304",
          "observed_name": "WO3",
          "confidence": 1,
          "source": "Inferlink Extraction v2"
        },
        "ore": {
          "unit": {
            "normalized_uri": "https://minmod.isi.edu/resource/Q200",
            "observed_name": "kt",
            "confidence": 1,
            "source": "Inferlink Extraction v2"
          },
          "value": 1097000.0
        },
        "grade": {
          "unit": {
            "normalized_uri": "https://minmod.isi.edu/resource/Q201",
            "observed_name": "%",
            "confidence": 1,
            "source": "Inferlink Extraction v2"
          },
          "value": 0.562
        },
        "cutoff_grade": {
          "unit": {
            "normalized_uri": "https://minmod.isi.edu/resource/Q201",
            "observed_name": "%",
            "confidence": 1,
            "source": "Inferlink Extraction v2"
          },
          "value": 0.3
        },
        "contained_metal": 6165.14,
        "reference": {
          "document": {
            "title": "NI 43-101 Technical Report for the Springer Project in Nevada, United States dated May 2009.pdf",
            "authors": [
              "Bart A. Stryhas"
            ],
            "year": 2009,
            "month": 5,
            "description": "This report provides a comprehensive review of the historical exploration activities at the Springer Facility in Nevada and a current resource estimate based on drilling data.",
            "uri": "https://api.cdr.land/v1/docs/documents/02204021e5b0dfc7ef8b406b88bacc57065753c872ac9722011e56da8d3fa9f1dd"
          },
          "page_info": [
            {
              "page": 7
            }
          ]
        },
        "date": "2009-5",
        "zone": "sutton i & ii"
      },
      {
        "commodity": {
          "normalized_uri": "https://minmod.isi.edu/resource/Q615",
          "observed_name": "tungsten",
          "confidence": 1,
          "source": "Inferlink Extraction v2"
        },
        "category": [
          {
            "normalized_uri": "https://minmod.isi.edu/resource/Indicated",
            "observed_name": "indicated",
            "confidence": 1,
            "source": "Inferlink Extraction v2"
          }
        ],
        "material_form": {
          "normalized_uri": "https://minmod.isi.edu/resource/Q1304",
          "observed_name": "WO3",
          "confidence": 1,
          "source": "Inferlink Extraction v2"
        },
        "ore": {
          "unit": {
            "normalized_uri": "https://minmod.isi.edu/resource/Q200",
            "observed_name": "kt",
            "confidence": 1,
            "source": "Inferlink Extraction v2"
          },
          "value": 274000.0
        },
        "grade": {
          "unit": {
            "normalized_uri": "https://minmod.isi.edu/resource/Q201",
            "observed_name": "%",
            "confidence": 1,
            "source": "Inferlink Extraction v2"
          },
          "value": 0.619
        },
        "cutoff_grade": {
          "unit": {
            "normalized_uri": "https://minmod.isi.edu/resource/Q201",
            "observed_name": "%",
            "confidence": 1,
            "source": "Inferlink Extraction v2"
          },
          "value": 0.3
        },
        "contained_metal": 1696.06,
        "reference": {
          "document": {
            "title": "NI 43-101 Technical Report for the Springer Project in Nevada, United States dated May 2009.pdf",
            "authors": [
              "Bart A. Stryhas"
            ],
            "year": 2009,
            "month": 5,
            "description": "This report provides a comprehensive review of the historical exploration activities at the Springer Facility in Nevada and a current resource estimate based on drilling data.",
            "uri": "https://api.cdr.land/v1/docs/documents/02204021e5b0dfc7ef8b406b88bacc57065753c872ac9722011e56da8d3fa9f1dd"
          },
          "page_info": [
            {
              "page": 7
            }
          ]
        },
        "date": "2009-5",
        "zone": "sutton i & ii"
      }
    ],
    "deposit_type_candidate": [
      {
        "observed_name": "Skarn",
        "normalized_uri": "https://minmod.isi.edu/resource/Q447",
        "source": "Inferlink Extraction v2",
        "confidence": 1.0
      }
    ]
  }
]