[
  {
    "source_id": "https://doi.org/10.5382/econgeo.4950",
    "record_id": "Brown's-Brown's East",
    "name": "Brown's-Brown's East",
    "location_info": {
      "country": [
        {
          "source": "SAND",
          "confidence": 1.0,
          "observed_name": "Australia",
          "normalized_uri": "https://minmod.isi.edu/resource/Q1013"
        }
      ],
      "crs": {
        "source": "SAND",
        "confidence": 0.8,
        "normalized_uri": "https://minmod.isi.edu/resource/Q701"
      }
    },
    "deposit_type_candidate": [
      {
        "source": "SAND",
        "confidence": 0.0,
        "observed_name": "Magmatic Sulphide"
      },
      {
        "source": "SAND",
        "confidence": 0.0,
        "observed_name": "Sediment-hosted polymetallic"
      }
    ],
    "mineral_inventory": [
      {
        "reference": {
          "document": {
            "doi": "10.5382/econgeo.4950",
            "uri": "https://doi.org/10.5382/econgeo.4950",
            "title": "The New Century for Nickel Resources, Reserves, and Mining: Reassessing the Sustainability of the Devil’s Metal"
          }
        },
        "commodity": {
          "source": "SAND",
          "confidence": 1.0,
          "observed_name": "%Cu",
          "normalized_uri": "https://minmod.isi.edu/resource/Q538"
        },
        "category": [
          {
            "source": "SAND",
            "confidence": 1.0,
            "observed_name": "Measured",
            "normalized_uri": "https://minmod.isi.edu/resource/Measured"
          }
        ],
        "grade": {
          "value": 0.49,
          "unit": {
            "source": "SAND",
            "confidence": 1.0,
            "observed_name": "%Cu",
            "normalized_uri": "https://minmod.isi.edu/resource/Q201"
          }
        },
        "ore": {
          "value": 10.1,
          "unit": {
            "source": "SAND",
            "confidence": 1.0,
            "observed_name": "Mt",
            "normalized_uri": "https://minmod.isi.edu/resource/Q202"
          }
        }
      },
      {
        "reference": {
          "document": {
            "doi": "10.5382/econgeo.4950",
            "uri": "https://doi.org/10.5382/econgeo.4950",
            "title": "The New Century for Nickel Resources, Reserves, and Mining: Reassessing the Sustainability of the Devil’s Metal"
          }
        },
        "commodity": {
          "source": "SAND",
          "confidence": 1.0,
          "observed_name": "g/t Ag",
          "normalized_uri": "https://minmod.isi.edu/resource/Q585"
        },
        "category": [
          {
            "source": "SAND",
            "confidence": 1.0,
            "observed_name": "Measured",
            "normalized_uri": "https://minmod.isi.edu/resource/Measured"
          }
        ],
        "grade": {
          "value": 10.5,
          "unit": {
            "source": "SAND",
            "confidence": 1.0,
            "observed_name": "g/t Ag",
            "normalized_uri": "https://minmod.isi.edu/resource/Q203"
          }
        },
        "ore": {
          "value": 10.1,
          "unit": {
            "source": "SAND",
            "confidence": 1.0,
            "observed_name": "Mt",
            "normalized_uri": "https://minmod.isi.edu/resource/Q202"
          }
        }
      },
      {
        "reference": {
          "document": {
            "doi": "10.5382/econgeo.4950",
            "uri": "https://doi.org/10.5382/econgeo.4950",
            "title": "The New Century for Nickel Resources, Reserves, and Mining: Reassessing the Sustainability of the Devil’s Metal"
          }
        },
        "commodity": {
          "source": "SAND",
          "confidence": 1.0,
          "observed_name": "%Pb",
          "normalized_uri": "https://minmod.isi.edu/resource/Q565"
        },
        "category": [
          {
            "source": "SAND",
            "confidence": 1.0,
            "observed_name": "Measured",
            "normalized_uri": "https://minmod.isi.edu/resource/Measured"
          }
        ],
        "grade": {
          "value": 3.32,
          "unit": {
            "source": "SAND",
            "confidence": 1.0,
            "observed_name": "%Pb",
            "normalized_uri": "https://minmod.isi.edu/resource/Q201"
          }
        },
        "ore": {
          "value": 10.1,
          "unit": {
            "source": "SAND",
            "confidence": 1.0,
            "observed_name": "Mt",
            "normalized_uri": "https://minmod.isi.edu/resource/Q202"
          }
        }
      },
      {
        "reference": {
          "document": {
            "doi": "10.5382/econgeo.4950",
            "uri": "https://doi.org/10.5382/econgeo.4950",
            "title": "The New Century for Nickel Resources, Reserves, and Mining: Reassessing the Sustainability of the Devil’s Metal"
          }
        },
        "commodity": {
          "source": "SAND",
          "confidence": 1.0,
          "observed_name": "%Zn",
          "normalized_uri": "https://minmod.isi.edu/resource/Q589"
        },
        "category": [
          {
            "source": "SAND",
            "confidence": 1.0,
            "observed_name": "Measured",
            "normalized_uri": "https://minmod.isi.edu/resource/Measured"
          }
        ],
        "grade": {
          "value": 0.54,
          "unit": {
            "source": "SAND",
            "confidence": 1.0,
            "observed_name": "%Zn",
            "normalized_uri": "https://minmod.isi.edu/resource/Q201"
          }
        },
        "ore": {
          "value": 10.1,
          "unit": {
            "source": "SAND",
            "confidence": 1.0,
            "observed_name": "Mt",
            "normalized_uri": "https://minmod.isi.edu/resource/Q202"
          }
        }
      },
      {
        "reference": {
          "document": {
            "doi": "10.5382/econgeo.4950",
            "uri": "https://doi.org/10.5382/econgeo.4950",
            "title": "The New Century for Nickel Resources, Reserves, and Mining: Reassessing the Sustainability of the Devil’s Metal"
          }
        },
        "commodity": {
          "source": "SAND",
          "confidence": 1.0,
          "observed_name": "%Ni",
          "normalized_uri": "https://minmod.isi.edu/resource/Q578"
        },
        "category": [
          {
            "source": "SAND",
            "confidence": 1.0,
            "observed_name": "Measured",
            "normalized_uri": "https://minmod.isi.edu/resource/Measured"
          }
        ],
        "grade": {
          "value": 0.1,
          "unit": {
            "source": "SAND",
            "confidence": 1.0,
            "observed_name": "%Ni",
            "normalized_uri": "https://minmod.isi.edu/resource/Q201"
          }
        },
        "ore": {
          "value": 10.1,
          "unit": {
            "source": "SAND",
            "confidence": 1.0,
            "observed_name": "Mt",
            "normalized_uri": "https://minmod.isi.edu/resource/Q202"
          }
        }
      },
      {
        "reference": {
          "document": {
            "doi": "10.5382/econgeo.4950",
            "uri": "https://doi.org/10.5382/econgeo.4950",
            "title": "The New Century for Nickel Resources, Reserves, and Mining: Reassessing the Sustainability of the Devil’s Metal"
          }
        },
        "commodity": {
          "source": "SAND",
          "confidence": 1.0,
          "observed_name": "%Co",
          "normalized_uri": "https://minmod.isi.edu/resource/Q537"
        },
        "category": [
          {
            "source": "SAND",
            "confidence": 1.0,
            "observed_name": "Measured",
            "normalized_uri": "https://minmod.isi.edu/resource/Measured"
          }
        ],
        "grade": {
          "value": 0.12,
          "unit": {
            "source": "SAND",
            "confidence": 1.0,
            "observed_name": "%Co",
            "normalized_uri": "https://minmod.isi.edu/resource/Q201"
          }
        },
        "ore": {
          "value": 10.1,
          "unit": {
            "source": "SAND",
            "confidence": 1.0,
            "observed_name": "Mt",
            "normalized_uri": "https://minmod.isi.edu/resource/Q202"
          }
        }
      },
      {
        "reference": {
          "document": {
            "doi": "10.5382/econgeo.4950",
            "uri": "https://doi.org/10.5382/econgeo.4950",
            "title": "The New Century for Nickel Resources, Reserves, and Mining: Reassessing the Sustainability of the Devil’s Metal"
          }
        },
        "commodity": {
          "source": "SAND",
          "confidence": 1.0,
          "observed_name": "%Cu",
          "normalized_uri": "https://minmod.isi.edu/resource/Q538"
        },
        "category": [
          {
            "source": "SAND",
            "confidence": 1.0,
            "observed_name": "Indicated",
            "normalized_uri": "https://minmod.isi.edu/resource/Indicated"
          }
        ],
        "grade": {
          "value": 0.38,
          "unit": {
            "source": "SAND",
            "confidence": 1.0,
            "observed_name": "%Cu",
            "normalized_uri": "https://minmod.isi.edu/resource/Q201"
          }
        },
        "ore": {
          "value": 22.7,
          "unit": {
            "source": "SAND",
            "confidence": 1.0,
            "observed_name": "Mt",
            "normalized_uri": "https://minmod.isi.edu/resource/Q202"
          }
        }
      },
      {
        "reference": {
          "document": {
            "doi": "10.5382/econgeo.4950",
            "uri": "https://doi.org/10.5382/econgeo.4950",
            "title": "The New Century for Nickel Resources, Reserves, and Mining: Reassessing the Sustainability of the Devil’s Metal"
          }
        },
        "commodity": {
          "source": "SAND",
          "confidence": 1.0,
          "observed_name": "g/t Ag",
          "normalized_uri": "https://minmod.isi.edu/resource/Q585"
        },
        "category": [
          {
            "source": "SAND",
            "confidence": 1.0,
            "observed_name": "Indicated",
            "normalized_uri": "https://minmod.isi.edu/resource/Indicated"
          }
        ],
        "grade": {
          "value": 13.8,
          "unit": {
            "source": "SAND",
            "confidence": 1.0,
            "observed_name": "g/t Ag",
            "normalized_uri": "https://minmod.isi.edu/resource/Q203"
          }
        },
        "ore": {
          "value": 22.7,
          "unit": {
            "source": "SAND",
            "confidence": 1.0,
            "observed_name": "Mt",
            "normalized_uri": "https://minmod.isi.edu/resource/Q202"
          }
        }
      },
      {
        "reference": {
          "document": {
            "doi": "10.5382/econgeo.4950",
            "uri": "https://doi.org/10.5382/econgeo.4950",
            "title": "The New Century for Nickel Resources, Reserves, and Mining: Reassessing the Sustainability of the Devil’s Metal"
          }
        },
        "commodity": {
          "source": "SAND",
          "confidence": 1.0,
          "observed_name": "%Pb",
          "normalized_uri": "https://minmod.isi.edu/resource/Q565"
        },
        "category": [
          {
            "source": "SAND",
            "confidence": 1.0,
            "observed_name": "Indicated",
            "normalized_uri": "https://minmod.isi.edu/resource/Indicated"
          }
        ],
        "grade": {
          "value": 3.47,
          "unit": {
            "source": "SAND",
            "confidence": 1.0,
            "observed_name": "%Pb",
            "normalized_uri": "https://minmod.isi.edu/resource/Q201"
          }
        },
        "ore": {
          "value": 22.7,
          "unit": {
            "source": "SAND",
            "confidence": 1.0,
            "observed_name": "Mt",
            "normalized_uri": "https://minmod.isi.edu/resource/Q202"
          }
        }
      },
      {
        "reference": {
          "document": {
            "doi": "10.5382/econgeo.4950",
            "uri": "https://doi.org/10.5382/econgeo.4950",
            "title": "The New Century for Nickel Resources, Reserves, and Mining: Reassessing the Sustainability of the Devil’s Metal"
          }
        },
        "commodity": {
          "source": "SAND",
          "confidence": 1.0,
          "observed_name": "%Zn",
          "normalized_uri": "https://minmod.isi.edu/resource/Q589"
        },
        "category": [
          {
            "source": "SAND",
            "confidence": 1.0,
            "observed_name": "Indicated",
            "normalized_uri": "https://minmod.isi.edu/resource/Indicated"
          }
        ],
        "grade": {
          "value": 0.71,
          "unit": {
            "source": "SAND",
            "confidence": 1.0,
            "observed_name": "%Zn",
            "normalized_uri": "https://minmod.isi.edu/resource/Q201"
          }
        },
        "ore": {
          "value": 22.7,
          "unit": {
            "source": "SAND",
            "confidence": 1.0,
            "observed_name": "Mt",
            "normalized_uri": "https://minmod.isi.edu/resource/Q202"
          }
        }
      },
      {
        "reference": {
          "document": {
            "doi": "10.5382/econgeo.4950",
            "uri": "https://doi.org/10.5382/econgeo.4950",
            "title": "The New Century for Nickel Resources, Reserves, and Mining: Reassessing the Sustainability of the Devil’s Metal"
          }
        },
        "commodity": {
          "source": "SAND",
          "confidence": 1.0,
          "observed_name": "%Ni",
          "normalized_uri": "https://minmod.isi.edu/resource/Q578"
        },
        "category": [
          {
            "source": "SAND",
            "confidence": 1.0,
            "observed_name": "Indicated",
            "normalized_uri": "https://minmod.isi.edu/resource/Indicated"
          }
        ],
        "grade": {
          "value": 0.09,
          "unit": {
            "source": "SAND",
            "confidence": 1.0,
            "observed_name": "%Ni",
            "normalized_uri": "https://minmod.isi.edu/resource/Q201"
          }
        },
        "ore": {
          "value": 22.7,
          "unit": {
            "source": "SAND",
            "confidence": 1.0,
            "observed_name": "Mt",
            "normalized_uri": "https://minmod.isi.edu/resource/Q202"
          }
        }
      },
      {
        "reference": {
          "document": {
            "doi": "10.5382/econgeo.4950",
            "uri": "https://doi.org/10.5382/econgeo.4950",
            "title": "The New Century for Nickel Resources, Reserves, and Mining: Reassessing the Sustainability of the Devil’s Metal"
          }
        },
        "commodity": {
          "source": "SAND",
          "confidence": 1.0,
          "observed_name": "%Co",
          "normalized_uri": "https://minmod.isi.edu/resource/Q537"
        },
        "category": [
          {
            "source": "SAND",
            "confidence": 1.0,
            "observed_name": "Indicated",
            "normalized_uri": "https://minmod.isi.edu/resource/Indicated"
          }
        ],
        "grade": {
          "value": 0.11,
          "unit": {
            "source": "SAND",
            "confidence": 1.0,
            "observed_name": "%Co",
            "normalized_uri": "https://minmod.isi.edu/resource/Q201"
          }
        },
        "ore": {
          "value": 22.7,
          "unit": {
            "source": "SAND",
            "confidence": 1.0,
            "observed_name": "Mt",
            "normalized_uri": "https://minmod.isi.edu/resource/Q202"
          }
        }
      },
      {
        "reference": {
          "document": {
            "doi": "10.5382/econgeo.4950",
            "uri": "https://doi.org/10.5382/econgeo.4950",
            "title": "The New Century for Nickel Resources, Reserves, and Mining: Reassessing the Sustainability of the Devil’s Metal"
          }
        },
        "commodity": {
          "source": "SAND",
          "confidence": 1.0,
          "observed_name": "%Cu",
          "normalized_uri": "https://minmod.isi.edu/resource/Q538"
        },
        "category": [
          {
            "source": "SAND",
            "confidence": 1.0,
            "observed_name": "Inferred",
            "normalized_uri": "https://minmod.isi.edu/resource/Inferred"
          }
        ],
        "grade": {
          "value": 0.65,
          "unit": {
            "source": "SAND",
            "confidence": 1.0,
            "observed_name": "%Cu",
            "normalized_uri": "https://minmod.isi.edu/resource/Q201"
          }
        },
        "ore": {
          "value": 26.7,
          "unit": {
            "source": "SAND",
            "confidence": 1.0,
            "observed_name": "Mt",
            "normalized_uri": "https://minmod.isi.edu/resource/Q202"
          }
        }
      },
      {
        "reference": {
          "document": {
            "doi": "10.5382/econgeo.4950",
            "uri": "https://doi.org/10.5382/econgeo.4950",
            "title": "The New Century for Nickel Resources, Reserves, and Mining: Reassessing the Sustainability of the Devil’s Metal"
          }
        },
        "commodity": {
          "source": "SAND",
          "confidence": 1.0,
          "observed_name": "g/t Ag",
          "normalized_uri": "https://minmod.isi.edu/resource/Q585"
        },
        "category": [
          {
            "source": "SAND",
            "confidence": 1.0,
            "observed_name": "Inferred",
            "normalized_uri": "https://minmod.isi.edu/resource/Inferred"
          }
        ],
        "grade": {
          "value": 14.3,
          "unit": {
            "source": "SAND",
            "confidence": 1.0,
            "observed_name": "g/t Ag",
            "normalized_uri": "https://minmod.isi.edu/resource/Q203"
          }
        },
        "ore": {
          "value": 26.7,
          "unit": {
            "source": "SAND",
            "confidence": 1.0,
            "observed_name": "Mt",
            "normalized_uri": "https://minmod.isi.edu/resource/Q202"
          }
        }
      },
      {
        "reference": {
          "document": {
            "doi": "10.5382/econgeo.4950",
            "uri": "https://doi.org/10.5382/econgeo.4950",
            "title": "The New Century for Nickel Resources, Reserves, and Mining: Reassessing the Sustainability of the Devil’s Metal"
          }
        },
        "commodity": {
          "source": "SAND",
          "confidence": 1.0,
          "observed_name": "%Pb",
          "normalized_uri": "https://minmod.isi.edu/resource/Q565"
        },
        "category": [
          {
            "source": "SAND",
            "confidence": 1.0,
            "observed_name": "Inferred",
            "normalized_uri": "https://minmod.isi.edu/resource/Inferred"
          }
        ],
        "grade": {
          "value": 2.7,
          "unit": {
            "source": "SAND",
            "confidence": 1.0,
            "observed_name": "%Pb",
            "normalized_uri": "https://minmod.isi.edu/resource/Q201"
          }
        },
        "ore": {
          "value": 26.7,
          "unit": {
            "source": "SAND",
            "confidence": 1.0,
            "observed_name": "Mt",
            "normalized_uri": "https://minmod.isi.edu/resource/Q202"
          }
        }
      },
      {
        "reference": {
          "document": {
            "doi": "10.5382/econgeo.4950",
            "uri": "https://doi.org/10.5382/econgeo.4950",
            "title": "The New Century for Nickel Resources, Reserves, and Mining: Reassessing the Sustainability of the Devil’s Metal"
          }
        },
        "commodity": {
          "source": "SAND",
          "confidence": 1.0,
          "observed_name": "%Ni",
          "normalized_uri": "https://minmod.isi.edu/resource/Q578"
        },
        "category": [
          {
            "source": "SAND",
            "confidence": 1.0,
            "observed_name": "Inferred",
            "normalized_uri": "https://minmod.isi.edu/resource/Inferred"
          }
        ],
        "grade": {
          "value": 0.09,
          "unit": {
            "source": "SAND",
            "confidence": 1.0,
            "observed_name": "%Ni",
            "normalized_uri": "https://minmod.isi.edu/resource/Q201"
          }
        },
        "ore": {
          "value": 26.7,
          "unit": {
            "source": "SAND",
            "confidence": 1.0,
            "observed_name": "Mt",
            "normalized_uri": "https://minmod.isi.edu/resource/Q202"
          }
        }
      },
      {
        "reference": {
          "document": {
            "doi": "10.5382/econgeo.4950",
            "uri": "https://doi.org/10.5382/econgeo.4950",
            "title": "The New Century for Nickel Resources, Reserves, and Mining: Reassessing the Sustainability of the Devil’s Metal"
          }
        },
        "commodity": {
          "source": "SAND",
          "confidence": 1.0,
          "observed_name": "%Co",
          "normalized_uri": "https://minmod.isi.edu/resource/Q537"
        },
        "category": [
          {
            "source": "SAND",
            "confidence": 1.0,
            "observed_name": "Inferred",
            "normalized_uri": "https://minmod.isi.edu/resource/Inferred"
          }
        ],
        "grade": {
          "value": 0.09,
          "unit": {
            "source": "SAND",
            "confidence": 1.0,
            "observed_name": "%Co",
            "normalized_uri": "https://minmod.isi.edu/resource/Q201"
          }
        },
        "ore": {
          "value": 26.7,
          "unit": {
            "source": "SAND",
            "confidence": 1.0,
            "observed_name": "Mt",
            "normalized_uri": "https://minmod.isi.edu/resource/Q202"
          }
        }
      }
    ],
    "reference": [
      {
        "document": {
          "doi": "10.5382/econgeo.4950",
          "uri": "https://doi.org/10.5382/econgeo.4950",
          "title": "The New Century for Nickel Resources, Reserves, and Mining: Reassessing the Sustainability of the Devil’s Metal"
        }
      }
    ],
    "created_by": "https://minmod.isi.edu/users/s/usc",
    "modified_at": "2024-09-20T00:00:00Z"
  },
  {
    "source_id": "https://doi.org/10.5382/econgeo.4950",
    "record_id": "Clarion-Clipperton (Russian-led JV)",
    "name": "Clarion-Clipperton (Russian-led JV)",
    "location_info": {
      "country": [
        {
          "source": "SAND",
          "confidence": 0.5470739577882434,
          "observed_name": "Int'l Waters",
          "normalized_uri": "https://minmod.isi.edu/resource/Q1235"
        }
      ],
      "crs": {
        "source": "SAND",
        "confidence": 0.8,
        "normalized_uri": "https://minmod.isi.edu/resource/Q701"
      }
    },
    "deposit_type_candidate": [
      {
        "source": "SAND",
        "confidence": 0.0,
        "observed_name": "Hydrothermal Ni"
      },
      {
        "source": "SAND",
        "confidence": 0.0,
        "observed_name": "Manganese nodules"
      }
    ],
    "mineral_inventory": [
      {
        "reference": {
          "document": {
            "doi": "10.5382/econgeo.4950",
            "uri": "https://doi.org/10.5382/econgeo.4950",
            "title": "The New Century for Nickel Resources, Reserves, and Mining: Reassessing the Sustainability of the Devil’s Metal"
          }
        },
        "commodity": {
          "source": "SAND",
          "confidence": 1.0,
          "observed_name": "%Cu",
          "normalized_uri": "https://minmod.isi.edu/resource/Q538"
        },
        "category": [
          {
            "source": "SAND",
            "confidence": 1.0,
            "observed_name": "Inferred",
            "normalized_uri": "https://minmod.isi.edu/resource/Inferred"
          }
        ],
        "grade": {
          "value": 1.29080118694362,
          "unit": {
            "source": "SAND",
            "confidence": 1.0,
            "observed_name": "%Cu",
            "normalized_uri": "https://minmod.isi.edu/resource/Q201"
          }
        },
        "ore": {
          "value": 33.7,
          "unit": {
            "source": "SAND",
            "confidence": 1.0,
            "observed_name": "Mt",
            "normalized_uri": "https://minmod.isi.edu/resource/Q202"
          }
        }
      },
      {
        "reference": {
          "document": {
            "doi": "10.5382/econgeo.4950",
            "uri": "https://doi.org/10.5382/econgeo.4950",
            "title": "The New Century for Nickel Resources, Reserves, and Mining: Reassessing the Sustainability of the Devil’s Metal"
          }
        },
        "commodity": {
          "source": "SAND",
          "confidence": 1.0,
          "observed_name": "%Ni",
          "normalized_uri": "https://minmod.isi.edu/resource/Q578"
        },
        "category": [
          {
            "source": "SAND",
            "confidence": 1.0,
            "observed_name": "Inferred",
            "normalized_uri": "https://minmod.isi.edu/resource/Inferred"
          }
        ],
        "grade": {
          "value": 1.3145400593471808,
          "unit": {
            "source": "SAND",
            "confidence": 1.0,
            "observed_name": "%Ni",
            "normalized_uri": "https://minmod.isi.edu/resource/Q201"
          }
        },
        "ore": {
          "value": 33.7,
          "unit": {
            "source": "SAND",
            "confidence": 1.0,
            "observed_name": "Mt",
            "normalized_uri": "https://minmod.isi.edu/resource/Q202"
          }
        }
      },
      {
        "reference": {
          "document": {
            "doi": "10.5382/econgeo.4950",
            "uri": "https://doi.org/10.5382/econgeo.4950",
            "title": "The New Century for Nickel Resources, Reserves, and Mining: Reassessing the Sustainability of the Devil’s Metal"
          }
        },
        "commodity": {
          "source": "SAND",
          "confidence": 1.0,
          "observed_name": "%Co",
          "normalized_uri": "https://minmod.isi.edu/resource/Q537"
        },
        "category": [
          {
            "source": "SAND",
            "confidence": 1.0,
            "observed_name": "Inferred",
            "normalized_uri": "https://minmod.isi.edu/resource/Inferred"
          }
        ],
        "grade": {
          "value": 0.1572700296735905,
          "unit": {
            "source": "SAND",
            "confidence": 1.0,
            "observed_name": "%Co",
            "normalized_uri": "https://minmod.isi.edu/resource/Q201"
          }
        },
        "ore": {
          "value": 33.7,
          "unit": {
            "source": "SAND",
            "confidence": 1.0,
            "observed_name": "Mt",
            "normalized_uri": "https://minmod.isi.edu/resource/Q202"
          }
        }
      },
      {
        "reference": {
          "document": {
            "doi": "10.5382/econgeo.4950",
            "uri": "https://doi.org/10.5382/econgeo.4950",
            "title": "The New Century for Nickel Resources, Reserves, and Mining: Reassessing the Sustainability of the Devil’s Metal"
          }
        },
        "commodity": {
          "source": "SAND",
          "confidence": 1.0,
          "observed_name": "%Mn",
          "normalized_uri": "https://minmod.isi.edu/resource/Q571"
        },
        "category": [
          {
            "source": "SAND",
            "confidence": 1.0,
            "observed_name": "Inferred",
            "normalized_uri": "https://minmod.isi.edu/resource/Inferred"
          }
        ],
        "grade": {
          "value": 32.64094955489614,
          "unit": {
            "source": "SAND",
            "confidence": 1.0,
            "observed_name": "%Mn",
            "normalized_uri": "https://minmod.isi.edu/resource/Q201"
          }
        },
        "ore": {
          "value": 33.7,
          "unit": {
            "source": "SAND",
            "confidence": 1.0,
            "observed_name": "Mt",
            "normalized_uri": "https://minmod.isi.edu/resource/Q202"
          }
        }
      }
    ],
    "reference": [
      {
        "document": {
          "doi": "10.5382/econgeo.4950",
          "uri": "https://doi.org/10.5382/econgeo.4950",
          "title": "The New Century for Nickel Resources, Reserves, and Mining: Reassessing the Sustainability of the Devil’s Metal"
        }
      }
    ],
    "created_by": "https://minmod.isi.edu/users/s/usc",
    "modified_at": "2024-09-20T00:00:00Z"
  },
  {
    "source_id": "https://doi.org/10.5382/econgeo.4950",
    "record_id": "Mindoro (Lower Kisluyan-Buraboy)",
    "name": "Mindoro (Lower Kisluyan-Buraboy)",
    "location_info": {
      "country": [
        {
          "source": "SAND",
          "confidence": 1.0,
          "observed_name": "Philippines",
          "normalized_uri": "https://minmod.isi.edu/resource/Q1173"
        }
      ],
      "crs": {
        "source": "SAND",
        "confidence": 0.8,
        "normalized_uri": "https://minmod.isi.edu/resource/Q701"
      }
    },
    "deposit_type_candidate": [
      {
        "source": "SAND",
        "confidence": 0.0,
        "observed_name": "Laterite"
      },
      {
        "source": "SAND",
        "confidence": 0.0,
        "observed_name": "Oxide-Hydrous Mg silicate"
      }
    ],
    "mineral_inventory": [
      {
        "reference": {
          "document": {
            "doi": "10.5382/econgeo.4950",
            "uri": "https://doi.org/10.5382/econgeo.4950",
            "title": "The New Century for Nickel Resources, Reserves, and Mining: Reassessing the Sustainability of the Devil’s Metal"
          }
        },
        "commodity": {
          "source": "SAND",
          "confidence": 1.0,
          "observed_name": "%Ni",
          "normalized_uri": "https://minmod.isi.edu/resource/Q578"
        },
        "category": [
          {
            "source": "SAND",
            "confidence": 1.0,
            "observed_name": "Indicated",
            "normalized_uri": "https://minmod.isi.edu/resource/Indicated"
          }
        ],
        "grade": {
          "value": 0.86,
          "unit": {
            "source": "SAND",
            "confidence": 1.0,
            "observed_name": "%Ni",
            "normalized_uri": "https://minmod.isi.edu/resource/Q201"
          }
        },
        "ore": {
          "value": 198.863,
          "unit": {
            "source": "SAND",
            "confidence": 1.0,
            "observed_name": "Mt",
            "normalized_uri": "https://minmod.isi.edu/resource/Q202"
          }
        }
      },
      {
        "reference": {
          "document": {
            "doi": "10.5382/econgeo.4950",
            "uri": "https://doi.org/10.5382/econgeo.4950",
            "title": "The New Century for Nickel Resources, Reserves, and Mining: Reassessing the Sustainability of the Devil’s Metal"
          }
        },
        "commodity": {
          "source": "SAND",
          "confidence": 1.0,
          "observed_name": "%Co",
          "normalized_uri": "https://minmod.isi.edu/resource/Q537"
        },
        "category": [
          {
            "source": "SAND",
            "confidence": 1.0,
            "observed_name": "Indicated",
            "normalized_uri": "https://minmod.isi.edu/resource/Indicated"
          }
        ],
        "grade": {
          "value": 0.05,
          "unit": {
            "source": "SAND",
            "confidence": 1.0,
            "observed_name": "%Co",
            "normalized_uri": "https://minmod.isi.edu/resource/Q201"
          }
        },
        "ore": {
          "value": 198.863,
          "unit": {
            "source": "SAND",
            "confidence": 1.0,
            "observed_name": "Mt",
            "normalized_uri": "https://minmod.isi.edu/resource/Q202"
          }
        }
      },
      {
        "reference": {
          "document": {
            "doi": "10.5382/econgeo.4950",
            "uri": "https://doi.org/10.5382/econgeo.4950",
            "title": "The New Century for Nickel Resources, Reserves, and Mining: Reassessing the Sustainability of the Devil’s Metal"
          }
        },
        "commodity": {
          "source": "SAND",
          "confidence": 1.0,
          "observed_name": "%Cr",
          "normalized_uri": "https://minmod.isi.edu/resource/Q519"
        },
        "category": [
          {
            "source": "SAND",
            "confidence": 1.0,
            "observed_name": "Indicated",
            "normalized_uri": "https://minmod.isi.edu/resource/Indicated"
          }
        ],
        "grade": {
          "value": 1.382077985302922,
          "unit": {
            "source": "SAND",
            "confidence": 1.0,
            "observed_name": "%Cr",
            "normalized_uri": "https://minmod.isi.edu/resource/Q201"
          }
        },
        "ore": {
          "value": 198.863,
          "unit": {
            "source": "SAND",
            "confidence": 1.0,
            "observed_name": "Mt",
            "normalized_uri": "https://minmod.isi.edu/resource/Q202"
          }
        }
      },
      {
        "reference": {
          "document": {
            "doi": "10.5382/econgeo.4950",
            "uri": "https://doi.org/10.5382/econgeo.4950",
            "title": "The New Century for Nickel Resources, Reserves, and Mining: Reassessing the Sustainability of the Devil’s Metal"
          }
        },
        "commodity": {
          "source": "SAND",
          "confidence": 1.0,
          "observed_name": "%Fe",
          "normalized_uri": "https://minmod.isi.edu/resource/Q561"
        },
        "category": [
          {
            "source": "SAND",
            "confidence": 1.0,
            "observed_name": "Indicated",
            "normalized_uri": "https://minmod.isi.edu/resource/Indicated"
          }
        ],
        "grade": {
          "value": 26.0,
          "unit": {
            "source": "SAND",
            "confidence": 1.0,
            "observed_name": "%Fe",
            "normalized_uri": "https://minmod.isi.edu/resource/Q201"
          }
        },
        "ore": {
          "value": 198.863,
          "unit": {
            "source": "SAND",
            "confidence": 1.0,
            "observed_name": "Mt",
            "normalized_uri": "https://minmod.isi.edu/resource/Q202"
          }
        }
      },
      {
        "reference": {
          "document": {
            "doi": "10.5382/econgeo.4950",
            "uri": "https://doi.org/10.5382/econgeo.4950",
            "title": "The New Century for Nickel Resources, Reserves, and Mining: Reassessing the Sustainability of the Devil’s Metal"
          }
        },
        "commodity": {
          "source": "SAND",
          "confidence": 1.0,
          "observed_name": "%SiO2",
          "normalized_uri": "https://minmod.isi.edu/resource/Q685"
        },
        "category": [
          {
            "source": "SAND",
            "confidence": 1.0,
            "observed_name": "Indicated",
            "normalized_uri": "https://minmod.isi.edu/resource/Indicated"
          }
        ],
        "grade": {
          "value": 25.49,
          "unit": {
            "source": "SAND",
            "confidence": 1.0,
            "observed_name": "%SiO2",
            "normalized_uri": "https://minmod.isi.edu/resource/Q201"
          }
        },
        "ore": {
          "value": 198.863,
          "unit": {
            "source": "SAND",
            "confidence": 1.0,
            "observed_name": "Mt",
            "normalized_uri": "https://minmod.isi.edu/resource/Q202"
          }
        }
      },
      {
        "reference": {
          "document": {
            "doi": "10.5382/econgeo.4950",
            "uri": "https://doi.org/10.5382/econgeo.4950",
            "title": "The New Century for Nickel Resources, Reserves, and Mining: Reassessing the Sustainability of the Devil’s Metal"
          }
        },
        "commodity": {
          "source": "SAND",
          "confidence": 1.0,
          "observed_name": "%Ni",
          "normalized_uri": "https://minmod.isi.edu/resource/Q578"
        },
        "category": [
          {
            "source": "SAND",
            "confidence": 1.0,
            "observed_name": "Probable",
            "normalized_uri": "https://minmod.isi.edu/resource/Probable"
          }
        ],
        "grade": {
          "value": 0.95,
          "unit": {
            "source": "SAND",
            "confidence": 1.0,
            "observed_name": "%Ni",
            "normalized_uri": "https://minmod.isi.edu/resource/Q201"
          }
        },
        "ore": {
          "value": 126.27,
          "unit": {
            "source": "SAND",
            "confidence": 1.0,
            "observed_name": "Mt",
            "normalized_uri": "https://minmod.isi.edu/resource/Q202"
          }
        }
      },
      {
        "reference": {
          "document": {
            "doi": "10.5382/econgeo.4950",
            "uri": "https://doi.org/10.5382/econgeo.4950",
            "title": "The New Century for Nickel Resources, Reserves, and Mining: Reassessing the Sustainability of the Devil’s Metal"
          }
        },
        "commodity": {
          "source": "SAND",
          "confidence": 1.0,
          "observed_name": "%Co",
          "normalized_uri": "https://minmod.isi.edu/resource/Q537"
        },
        "category": [
          {
            "source": "SAND",
            "confidence": 1.0,
            "observed_name": "Probable",
            "normalized_uri": "https://minmod.isi.edu/resource/Probable"
          }
        ],
        "grade": {
          "value": 0.06,
          "unit": {
            "source": "SAND",
            "confidence": 1.0,
            "observed_name": "%Co",
            "normalized_uri": "https://minmod.isi.edu/resource/Q201"
          }
        },
        "ore": {
          "value": 126.27,
          "unit": {
            "source": "SAND",
            "confidence": 1.0,
            "observed_name": "Mt",
            "normalized_uri": "https://minmod.isi.edu/resource/Q202"
          }
        }
      }
    ],
    "reference": [
      {
        "document": {
          "doi": "10.5382/econgeo.4950",
          "uri": "https://doi.org/10.5382/econgeo.4950",
          "title": "The New Century for Nickel Resources, Reserves, and Mining: Reassessing the Sustainability of the Devil’s Metal"
        }
      }
    ],
    "created_by": "https://minmod.isi.edu/users/s/usc",
    "modified_at": "2024-09-20T00:00:00Z"
  },
  {
    "source_id": "https://doi.org/10.5382/econgeo.4950",
    "record_id": "Severo-Konzhozerskoe",
    "name": "Severo-Konzhozerskoe",
    "location_info": {
      "country": [
        {
          "source": "SAND",
          "confidence": 1.0,
          "observed_name": "Russia",
          "normalized_uri": "https://minmod.isi.edu/resource/Q1181"
        }
      ],
      "crs": {
        "source": "SAND",
        "confidence": 0.8,
        "normalized_uri": "https://minmod.isi.edu/resource/Q701"
      }
    },
    "deposit_type_candidate": [
      {
        "source": "SAND",
        "confidence": 0.0,
        "observed_name": "Magmatic Sulphide"
      },
      {
        "source": "SAND",
        "confidence": 0.0,
        "observed_name": "Archean komatiite"
      }
    ],
    "mineral_inventory": [
      {
        "reference": {
          "document": {
            "doi": "10.5382/econgeo.4950",
            "uri": "https://doi.org/10.5382/econgeo.4950",
            "title": "The New Century for Nickel Resources, Reserves, and Mining: Reassessing the Sustainability of the Devil’s Metal"
          }
        },
        "commodity": {
          "source": "SAND",
          "confidence": 1.0,
          "observed_name": "%Ni",
          "normalized_uri": "https://minmod.isi.edu/resource/Q578"
        },
        "category": [
          {
            "source": "SAND",
            "confidence": 1.0,
            "observed_name": "Inferred",
            "normalized_uri": "https://minmod.isi.edu/resource/Inferred"
          }
        ],
        "grade": {
          "value": 0.35,
          "unit": {
            "source": "SAND",
            "confidence": 1.0,
            "observed_name": "%Ni",
            "normalized_uri": "https://minmod.isi.edu/resource/Q201"
          }
        },
        "ore": {
          "value": 8.0,
          "unit": {
            "source": "SAND",
            "confidence": 1.0,
            "observed_name": "Mt",
            "normalized_uri": "https://minmod.isi.edu/resource/Q202"
          }
        }
      }
    ],
    "reference": [
      {
        "document": {
          "doi": "10.5382/econgeo.4950",
          "uri": "https://doi.org/10.5382/econgeo.4950",
          "title": "The New Century for Nickel Resources, Reserves, and Mining: Reassessing the Sustainability of the Devil’s Metal"
        }
      }
    ],
    "created_by": "https://minmod.isi.edu/users/s/usc",
    "modified_at": "2024-09-20T00:00:00Z"
  },
  {
    "source_id": "https://doi.org/10.5382/econgeo.4950",
    "record_id": "Szklary",
    "name": "Szklary",
    "location_info": {
      "country": [
        {
          "source": "SAND",
          "confidence": 1.0,
          "observed_name": "Poland",
          "normalized_uri": "https://minmod.isi.edu/resource/Q1175"
        }
      ],
      "crs": {
        "source": "SAND",
        "confidence": 0.8,
        "normalized_uri": "https://minmod.isi.edu/resource/Q701"
      }
    },
    "deposit_type_candidate": [
      {
        "source": "SAND",
        "confidence": 0.0,
        "observed_name": "Laterite"
      },
      {
        "source": "SAND",
        "confidence": 0.0,
        "observed_name": "Hydrous Mg silicate-Clay silicate"
      }
    ],
    "mineral_inventory": [
      {
        "reference": {
          "document": {
            "doi": "10.5382/econgeo.4950",
            "uri": "https://doi.org/10.5382/econgeo.4950",
            "title": "The New Century for Nickel Resources, Reserves, and Mining: Reassessing the Sustainability of the Devil’s Metal"
          }
        },
        "commodity": {
          "source": "SAND",
          "confidence": 1.0,
          "observed_name": "%Ni",
          "normalized_uri": "https://minmod.isi.edu/resource/Q578"
        },
        "category": [
          {
            "source": "SAND",
            "confidence": 1.0,
            "observed_name": "Inferred",
            "normalized_uri": "https://minmod.isi.edu/resource/Inferred"
          }
        ],
        "grade": {
          "value": 0.6,
          "unit": {
            "source": "SAND",
            "confidence": 1.0,
            "observed_name": "%Ni",
            "normalized_uri": "https://minmod.isi.edu/resource/Q201"
          }
        },
        "ore": {
          "value": 16.8,
          "unit": {
            "source": "SAND",
            "confidence": 1.0,
            "observed_name": "Mt",
            "normalized_uri": "https://minmod.isi.edu/resource/Q202"
          }
        }
      }
    ],
    "reference": [
      {
        "document": {
          "doi": "10.5382/econgeo.4950",
          "uri": "https://doi.org/10.5382/econgeo.4950",
          "title": "The New Century for Nickel Resources, Reserves, and Mining: Reassessing the Sustainability of the Devil’s Metal"
        }
      }
    ],
    "created_by": "https://minmod.isi.edu/users/s/usc",
    "modified_at": "2024-09-20T00:00:00Z"
  },
  {
    "source_id": "https://doi.org/10.5382/econgeo.4950",
    "record_id": "Zapadno-Rybozero",
    "name": "Zapadno-Rybozero",
    "location_info": {
      "country": [
        {
          "source": "SAND",
          "confidence": 1.0,
          "observed_name": "Russia",
          "normalized_uri": "https://minmod.isi.edu/resource/Q1181"
        }
      ],
      "crs": {
        "source": "SAND",
        "confidence": 0.8,
        "normalized_uri": "https://minmod.isi.edu/resource/Q701"
      }
    },
    "deposit_type_candidate": [
      {
        "source": "SAND",
        "confidence": 0.0,
        "observed_name": "Magmatic Sulphide"
      },
      {
        "source": "SAND",
        "confidence": 0.0,
        "observed_name": "Archean komatiite"
      }
    ],
    "mineral_inventory": [
      {
        "reference": {
          "document": {
            "doi": "10.5382/econgeo.4950",
            "uri": "https://doi.org/10.5382/econgeo.4950",
            "title": "The New Century for Nickel Resources, Reserves, and Mining: Reassessing the Sustainability of the Devil’s Metal"
          }
        },
        "commodity": {
          "source": "SAND",
          "confidence": 1.0,
          "observed_name": "%Ni",
          "normalized_uri": "https://minmod.isi.edu/resource/Q578"
        },
        "category": [
          {
            "source": "SAND",
            "confidence": 1.0,
            "observed_name": "Inferred",
            "normalized_uri": "https://minmod.isi.edu/resource/Inferred"
          }
        ],
        "grade": {
          "value": 0.34,
          "unit": {
            "source": "SAND",
            "confidence": 1.0,
            "observed_name": "%Ni",
            "normalized_uri": "https://minmod.isi.edu/resource/Q201"
          }
        },
        "ore": {
          "value": 4.12,
          "unit": {
            "source": "SAND",
            "confidence": 1.0,
            "observed_name": "Mt",
            "normalized_uri": "https://minmod.isi.edu/resource/Q202"
          }
        }
      }
    ],
    "reference": [
      {
        "document": {
          "doi": "10.5382/econgeo.4950",
          "uri": "https://doi.org/10.5382/econgeo.4950",
          "title": "The New Century for Nickel Resources, Reserves, and Mining: Reassessing the Sustainability of the Devil’s Metal"
        }
      }
    ],
    "created_by": "https://minmod.isi.edu/users/s/usc",
    "modified_at": "2024-09-20T00:00:00Z"
  }
]